<?xml version="1.0" encoding="utf-8" ?>

<Defs>
  

  <ThingDef ParentName="ResourceBase">
    <defName>CoalOre</defName>
    <label>Coal</label>
    <description>Being one of the most common elements on planets with carbon-based lifeforms, coal has many desirable properites, such as serving as good fuel source.</description>
    <graphicData>
      <texPath>resources/coal</texPath>
       <graphicClass>Graphic_StackCount</graphicClass>
    </graphicData>
    <soundInteract>Stone_Drop</soundInteract>
    <soundDrop>Stone_Drop</soundDrop>
    <statBases>
      <MarketValue>2</MarketValue>
      <MaxHitPoints>100</MaxHitPoints>	  
      <Mass>0.5</Mass>
      <DeteriorationRate>2</DeteriorationRate>
	  <Beauty>-10</Beauty>	  
      <Flammability>1.0</Flammability>	  
    </statBases>
    <thingCategories>
      <li>ResourcesRaw</li>
    </thingCategories>
	</ThingDef>
	
	
 </Defs>
